{
  "_class": "shapeGroup",
  "clippingMaskMode": 0,
  "do_objectID": "4B72014D-A331-4497-8B7F-D7CAC67B93BE",
  "exportOptions": {
    "_class": "exportOptions",
    "do_objectID": "47BC7E27-B95D-4A5B-BB4B-13BD9CB1B16B",
    "exportFormats": [
    ],
    "includedLayerIds": [
    ],
    "layerOptions": 0,
    "shouldTrim": false
  },
  "frame": {
    "_class": "rect",
    "constrainProportions": true,
    "do_objectID": "7A650F70-B582-4414-A4C7-645B40EC0696",
    "height": 24,
    "width": 24,
    "x": 0,
    "y": 0
  },
  "hasClickThrough": false,
  "hasClippingMask": true,
  "isFlippedHorizontal": false,
  "isFlippedVertical": false,
  "isLocked": false,
  "isVisible": true,
  "layerListExpandedType": 0,
  "layers": [
    {
      "class": "oval",
      "id": "3D2AC953-A41A-4B74-9C15-15BD4B7096DB"
    },
    {
      "class": "oval",
      "id": "1E72CA41-28A1-422A-B623-F434690DCE50"
    }
  ],
  "name": "frame",
  "nameIsFixed": true,
  "resizingConstraint": 63,
  "resizingType": 0,
  "rotation": 0,
  "shouldBreakMaskChain": false,
  "style": {
    "_class": "style",
    "borders": [
      {
        "_class": "border",
        "color": {
          "_class": "color",
          "alpha": 1,
          "blue": 0.9607843137254902,
          "green": 0.9529411764705882,
          "red": 0.9450980392156862
        },
        "fillType": 0,
        "isEnabled": false,
        "position": 1,
        "thickness": 1
      }
    ],
    "do_objectID": "1FA15FAF-5EEF-4826-BD7E-C44B72B5353F",
    "endDecorationType": 0,
    "fills": [
      {
        "_class": "fill",
        "color": {
          "_class": "color",
          "alpha": 1,
          "blue": 0.847,
          "green": 0.847,
          "red": 0.847
        },
        "fillType": 0,
        "isEnabled": false,
        "noiseIndex": 0,
        "noiseIntensity": 0,
        "patternFillType": 1,
        "patternTileScale": 1
      }
    ],
    "miterLimit": 10,
    "startDecorationType": 0
  },
  "windingRule": 1
}