{
  "_class": "bitmap",
  "clippingMask": "{{0, 0}, {1, 1}}",
  "do_objectID": "B9E0091E-622F-4DBE-BC2C-084BB405ADF7",
  "exportOptions": {
    "_class": "exportOptions",
    "do_objectID": "3D603F05-6558-474F-B502-79BEC3104942",
    "exportFormats": [
    ],
    "includedLayerIds": [
    ],
    "layerOptions": 0,
    "shouldTrim": false
  },
  "fillReplacesImage": false,
  "frame": {
    "_class": "rect",
    "constrainProportions": true,
    "do_objectID": "2966362E-6287-41AF-B5C0-E51A6A1F3345",
    "height": 24,
    "width": 24,
    "x": 0,
    "y": 0
  },
  "image": {
    "_class": "MSJSONFileReference",
    "_ref": "images/a189d611f9cc504fd37a0ff228157ceaf7c7af88",
    "_ref_class": "MSImageData"
  },
  "isFlippedHorizontal": false,
  "isFlippedVertical": false,
  "isLocked": false,
  "isVisible": true,
  "layerListExpandedType": 0,
  "name": "logo-04",
  "nameIsFixed": false,
  "resizingConstraint": 63,
  "resizingType": 0,
  "rotation": 0,
  "shouldBreakMaskChain": false,
  "style": {
    "_class": "style",
    "do_objectID": "114A01DE-8364-4535-9C30-69CCCD4BFE0D",
    "endDecorationType": 0,
    "miterLimit": 10,
    "startDecorationType": 0
  }
}