{
  "_class": "symbolInstance",
  "do_objectID": "7842C0B8-3C63-4FC5-99D7-943484B32F37",
  "exportOptions": {
    "_class": "exportOptions",
    "do_objectID": "E15D3DB4-697C-4181-8672-8791DD4FF347",
    "exportFormats": [
    ],
    "includedLayerIds": [
    ],
    "layerOptions": 0,
    "shouldTrim": false
  },
  "frame": {
    "_class": "rect",
    "constrainProportions": true,
    "do_objectID": "FCF96C60-D641-4899-97D0-DFF3361E4942",
    "height": 40,
    "width": 40,
    "x": 20,
    "y": 0
  },
  "horizontalSpacing": 0,
  "isFlippedHorizontal": false,
  "isFlippedVertical": false,
  "isLocked": false,
  "isVisible": true,
  "layerListExpandedType": 0,
  "name": "bg",
  "nameIsFixed": true,
  "overrideValues": [
  ],
  "overrides": {
  },
  "resizingConstraint": 63,
  "resizingType": 0,
  "rotation": 0,
  "scale": 1,
  "shouldBreakMaskChain": false,
  "style": {
    "_class": "style",
    "do_objectID": "4F980EB0-AC8E-4737-98B6-140E4213E568",
    "endDecorationType": 0,
    "miterLimit": 10,
    "startDecorationType": 0
  },
  "symbolID": "85D60749-09C7-42DD-BDC0-93D9691529F1",
  "verticalSpacing": 0
}