{
  "_class": "group",
  "do_objectID": "1557465A-94BB-4C2C-AA89-8C36A88847D4",
  "exportOptions": {
    "_class": "exportOptions",
    "do_objectID": "86379152-B7EC-43AC-821D-C0EEBD4193E9",
    "exportFormats": [
    ],
    "includedLayerIds": [
    ],
    "layerOptions": 0,
    "shouldTrim": false
  },
  "frame": {
    "_class": "rect",
    "constrainProportions": false,
    "do_objectID": "27474393-D178-4973-BBAE-9B20EB0A55FC",
    "height": 30,
    "width": 375,
    "x": 0,
    "y": 0
  },
  "hasClickThrough": false,
  "isFlippedHorizontal": false,
  "isFlippedVertical": false,
  "isLocked": false,
  "isVisible": true,
  "layerListExpandedType": 0,
  "layers": [
    {
      "class": "symbolInstance",
      "id": "A0A98B82-3398-47EC-85DA-E35A4F0452B3"
    },
    {
      "class": "text",
      "id": "7A6AFB90-ABCF-4D55-AC5F-0883E3126563"
    }
  ],
  "name": "article/sectionTitle",
  "nameIsFixed": true,
  "resizingConstraint": 63,
  "resizingType": 0,
  "rotation": 0,
  "shouldBreakMaskChain": false,
  "style": {
    "_class": "style",
    "do_objectID": "C006F8E2-EDDD-4853-A814-198236D3267A",
    "endDecorationType": 0,
    "miterLimit": 10,
    "startDecorationType": 0
  }
}