{
  "_class": "group",
  "do_objectID": "9F2E1742-69D9-441D-B90C-12DE3042BC95",
  "exportOptions": {
    "_class": "exportOptions",
    "do_objectID": "2E4352AE-23E2-422D-AA41-FBF191F6C797",
    "exportFormats": [
    ],
    "includedLayerIds": [
    ],
    "layerOptions": 0,
    "shouldTrim": false
  },
  "frame": {
    "_class": "rect",
    "constrainProportions": false,
    "do_objectID": "5A2CB8B2-186A-4D9B-9512-A27A002B7D82",
    "height": 152,
    "width": 375,
    "x": 0,
    "y": 302
  },
  "hasClickThrough": false,
  "isFlippedHorizontal": false,
  "isFlippedVertical": false,
  "isLocked": false,
  "isVisible": true,
  "layerListExpandedType": 2,
  "layers": [
    {
      "class": "symbolInstance",
      "id": "9D5B4DCD-32FF-4900-9F8D-2CBE4542485C"
    },
    {
      "class": "group",
      "id": "675FF0CD-1643-432E-90D8-C4A67CCFBE19"
    },
    {
      "class": "text",
      "id": "C9FF5D96-CA4A-40E8-9984-99A44D5933CF"
    },
    {
      "class": "text",
      "id": "4010C89B-3DDC-4ABC-A69A-1B47981ECDB0"
    },
    {
      "class": "text",
      "id": "2137C250-C60D-485F-BE42-073F269019F5"
    },
    {
      "class": "text",
      "id": "5BE8760F-BD85-4C45-834E-DD669F8E8917"
    },
    {
      "class": "text",
      "id": "53246AF8-14AC-458B-80D9-43BF9B662367"
    },
    {
      "class": "text",
      "id": "7E87F8AB-4897-4B9A-8243-C97913E32F00"
    },
    {
      "class": "symbolInstance",
      "id": "F2B18387-E62F-46FD-A435-973214F9A813"
    }
  ],
  "name": "listing/comment",
  "nameIsFixed": true,
  "originalObjectID": "9FC64376-9AAA-41F3-B404-DA35C245C798",
  "resizingConstraint": 63,
  "resizingType": 0,
  "rotation": 0,
  "shouldBreakMaskChain": false,
  "style": {
    "_class": "style",
    "do_objectID": "7A68D814-1A14-408C-B168-CEF36E062B58",
    "endDecorationType": 0,
    "miterLimit": 10,
    "startDecorationType": 0
  }
}