{
  "_class": "group",
  "do_objectID": "68EABFD5-A1D1-492D-9A95-3F0206D88AB0",
  "exportOptions": {
    "_class": "exportOptions",
    "do_objectID": "DEA18D62-6A10-43F9-9413-A8A4228A34D0",
    "exportFormats": [
    ],
    "includedLayerIds": [
    ],
    "layerOptions": 0,
    "shouldTrim": false
  },
  "frame": {
    "_class": "rect",
    "constrainProportions": false,
    "do_objectID": "1E7358C7-EFD2-4950-B688-BA6C0350E01E",
    "height": 210,
    "width": 375,
    "x": 0,
    "y": 0
  },
  "hasClickThrough": false,
  "isFlippedHorizontal": false,
  "isFlippedVertical": false,
  "isLocked": false,
  "isVisible": true,
  "layerListExpandedType": 0,
  "layers": [
    {
      "class": "symbolInstance",
      "id": "84E13776-1ED2-4B41-8F29-395AB2214F63"
    },
    {
      "class": "shapeGroup",
      "id": "B80DBC5E-80BA-453A-AD86-0AA24EDFD204"
    }
  ],
  "name": "thumb",
  "nameIsFixed": true,
  "resizingConstraint": 63,
  "resizingType": 0,
  "rotation": 0,
  "shouldBreakMaskChain": false,
  "style": {
    "_class": "style",
    "do_objectID": "C19EE777-937A-4D30-B31C-9C59BCDC9309",
    "endDecorationType": 0,
    "miterLimit": 10,
    "startDecorationType": 0
  },
  "userInfo": {
    "com.animaapp.stc-sketch-plugin": {
      "kModelPropertiesKey": {
      }
    }
  }
}