{
  "_class": "symbolInstance",
  "do_objectID": "F9F730C4-5705-4361-9119-D3914381566D",
  "exportOptions": {
    "_class": "exportOptions",
    "do_objectID": "68125C09-F731-4803-A973-A8D3A876C478",
    "exportFormats": [
    ],
    "includedLayerIds": [
    ],
    "layerOptions": 0,
    "shouldTrim": false
  },
  "frame": {
    "_class": "rect",
    "constrainProportions": false,
    "do_objectID": "CBE583A2-32BF-4BCD-BBD4-5F1C87F08873",
    "height": 4,
    "width": 375,
    "x": 0,
    "y": 72
  },
  "horizontalSpacing": 0,
  "isFlippedHorizontal": false,
  "isFlippedVertical": false,
  "isLocked": false,
  "isVisible": true,
  "layerListExpandedType": 0,
  "name": "shadow_header",
  "nameIsFixed": true,
  "overrideValues": [
  ],
  "overrides": {
  },
  "resizingConstraint": 63,
  "resizingType": 0,
  "rotation": 0,
  "scale": 1,
  "shouldBreakMaskChain": false,
  "style": {
    "_class": "style",
    "do_objectID": "14F920EE-87BA-4282-BE2B-5C9D65482F04",
    "endDecorationType": 0,
    "miterLimit": 10,
    "startDecorationType": 0
  },
  "symbolID": "4942176C-31E7-44BF-B9BE-9EAEEACFB03F",
  "userInfo": {
    "com.animaapp.stc-sketch-plugin": {
      "kModelPropertiesKey": {
      }
    }
  },
  "verticalSpacing": 0
}