{
  "_class": "shapeGroup",
  "clippingMaskMode": 0,
  "do_objectID": "943C48A3-9473-4ECB-90BB-03B7D7970913",
  "exportOptions": {
    "_class": "exportOptions",
    "do_objectID": "F5AC0B60-6B88-4497-81A3-CE56594D5AD1",
    "exportFormats": [
    ],
    "includedLayerIds": [
    ],
    "layerOptions": 0,
    "shouldTrim": false
  },
  "frame": {
    "_class": "rect",
    "constrainProportions": false,
    "do_objectID": "3F8DA16C-7115-4F35-B679-6FAB9EF9DC72",
    "height": 22,
    "width": 35,
    "x": 9,
    "y": 0
  },
  "hasClickThrough": false,
  "hasClippingMask": false,
  "isFlippedHorizontal": false,
  "isFlippedVertical": false,
  "isLocked": false,
  "isVisible": true,
  "layerListExpandedType": 1,
  "layers": [
    {
      "class": "rectangle",
      "id": "23A12FFF-E792-47CD-B176-6902A65216B4"
    }
  ],
  "name": "label-box",
  "nameIsFixed": false,
  "resizingConstraint": 63,
  "resizingType": 0,
  "rotation": 0,
  "shouldBreakMaskChain": false,
  "style": {
    "_class": "style",
    "do_objectID": "B09F206B-64D1-46A5-96BD-164FD1CF3EE5",
    "endDecorationType": 0,
    "fills": [
      {
        "_class": "fill",
        "color": {
          "_class": "color",
          "alpha": 1,
          "blue": 0,
          "green": 0.333333,
          "red": 1
        },
        "fillType": 0,
        "isEnabled": true,
        "noiseIndex": 0,
        "noiseIntensity": 0,
        "patternFillType": 1,
        "patternTileScale": 1
      }
    ],
    "miterLimit": 10,
    "sharedObjectID": "0C011B1C-F570-4562-BCA7-1ADB014A8EEB",
    "startDecorationType": 0
  },
  "userInfo": {
    "com.animaapp.stc-sketch-plugin": {
      "kModelPropertiesKey": {
      }
    }
  },
  "windingRule": 1
}